lang2py/__init__.py
lang2py/__main__.py
lang2py/_utils.py
lang2py-0.2.0.dist-info/METADATA
lang2py-0.2.0.dist-info/WHEEL
lang2py-0.2.0.dist-info/RECORD
